MANIFEST.in
setup.cfg
setup.py
ipytalos/__init__.py
ipytalos/_version.py
ipytalos/talos.py
ipytalos.egg-info/PKG-INFO
ipytalos.egg-info/SOURCES.txt
ipytalos.egg-info/dependency_links.txt
ipytalos.egg-info/not-zip-safe
ipytalos.egg-info/requires.txt
ipytalos.egg-info/top_level.txt
ipytalos/static/extension.js
ipytalos/static/index.js
ipytalos/static/index.js.map