Metadata-Version: 1.1
Name: ipytalos
Version: 0.1.0a0
Summary: A Custom Jupyter Widget Library
Home-page: https://github.com/qzchenwl/ipytalos
Author: qzchenwl
Author-email: qzchenwl@gmail.com
License: UNKNOWN
Keywords: ipython,jupyter,widgets
Platform: UNKNOWN
Classifier: Development Status :: 4 - Beta
Classifier: Framework :: IPython
Classifier: Intended Audience :: Developers
Classifier: Intended Audience :: Science/Research
Classifier: Topic :: Multimedia :: Graphics
Classifier: Programming Language :: Python :: 2
Classifier: Programming Language :: Python :: 2.7
Classifier: Programming Language :: Python :: 3
Classifier: Programming Language :: Python :: 3.3
Classifier: Programming Language :: Python :: 3.4
Classifier: Programming Language :: Python :: 3.5
